feincms3/__init__.py
feincms3/admin.py
feincms3/applications.py
feincms3/cleanse.py
feincms3/embedding.py
feincms3/inline_ckeditor.py
feincms3/mixins.py
feincms3/pages.py
feincms3/regions.py
feincms3/renderer.py
feincms3/shortcuts.py
feincms3/utils.py
feincms3/locale/de/LC_MESSAGES/django.mo
feincms3/locale/de/LC_MESSAGES/django.po
feincms3/locale/en/LC_MESSAGES/django.mo
feincms3/locale/en/LC_MESSAGES/django.po
feincms3/locale/fr/LC_MESSAGES/django.mo
feincms3/locale/fr/LC_MESSAGES/django.po
feincms3/locale/it/LC_MESSAGES/django.mo
feincms3/locale/it/LC_MESSAGES/django.po
feincms3/locale/nb_NO/LC_MESSAGES/django.mo
feincms3/locale/nb_NO/LC_MESSAGES/django.po
feincms3/plugins/__init__.py
feincms3/plugins/external.py
feincms3/plugins/html.py
feincms3/plugins/image.py
feincms3/plugins/old_richtext.py
feincms3/plugins/richtext.py
feincms3/plugins/snippet.py
feincms3/root/__init__.py
feincms3/root/middleware.py
feincms3/root/passthru.py
feincms3/static/feincms3/admin.css
feincms3/static/feincms3/admin.js
feincms3/static/feincms3/inline-ckeditor-contents.css
feincms3/static/feincms3/inline-ckeditor.css
feincms3/static/feincms3/inline-ckeditor.js
feincms3/static/feincms3/move-form.css
feincms3/static/feincms3/plugin-ckeditor.css
feincms3/static/feincms3/static-path-style.js
feincms3/templatetags/__init__.py
feincms3/templatetags/feincms3.py
feincms3-5.4.2.dist-info/METADATA
feincms3-5.4.2.dist-info/WHEEL
feincms3-5.4.2.dist-info/licenses/LICENSE
feincms3-5.4.2.dist-info/RECORD
